{
  "name": "Rozdział 9 - Kultura (cz. 2)",
  "date": "2026-03-13",
  "words": [
    {"pl":"gazeta dużego formatu (zwykle publikująca artykuły na wysokim poziomie)","en":"broadsheet newspaper"},
    {"pl":"cenzura","en":"censorship"},
    {"pl":"oszczerstwo, zniesławienie","en":"libel"},
    {"pl":"paparazzi (fotoreporterzy, którzy śledzą i fotografują znane osoby)","en":"paparazzi"},
    {"pl":"tabloid, gazeta brukowa","en":"tabloid newspaper"},
    {"pl":"troll internetowy (osoba, która w dyskusjach w internecie celowo zamieszcza wpisy mające wzbudzać w innych użytkownikach skrajne, negatywne emocje)","en":"troll"},
    {"pl":"widownia, publiczność","en":"audience"},
    {"pl":"kino","en":"cinema"},
    {"pl":"sala koncertowa","en":"concert hall"},
    {"pl":"wydarzenie będące częścią festiwalu","en":"festival event"},
    {"pl":"podanie ludowe","en":"folk tale"},
    {"pl":"stoisko z jedzeniem","en":"food stand"},
    {"pl":"festiwal alternatywny","en":"fringe festival"},
    {"pl":"sztuka, w której występuje jeden aktor, monodram","en":"one-man show"},
    {"pl":"opera","en":"opera"},
    {"pl":"pokaz, przegląd (filmowy)","en":"preview"},
    {"pl":"rzutnik, projektor","en":"projector"},
    {"pl":"recital (solowy wystąp, który wypełnia cały program koncertu)","en":"recital"},
    {"pl":"artysta uliczny","en":"street performer"},
    {"pl":"balet","en":"ballet"},
    {"pl":"galeria (np. sztuki)","en":"gallery"},
    {"pl":"multipleks, multikino","en":"multiplex cinema"},
    {"pl":"podkast (audycja radiowa, zazwyczaj cykliczna, zamieszczona w internecie)","en":"podcast"},
    {"pl":"symfonia","en":"symphony"},
    {"pl":"coroczny, doroczny","en":"annual"},
    {"pl":"panna młoda","en":"bride"},
    {"pl":"ceremonia, uroczystość","en":"ceremony"},
    {"pl":"powszechny","en":"common"},
    {"pl":"wydarzenie kulturalne","en":"cultural event"},
    {"pl":"powszechny, przyjęty, zwyczajowy","en":"customary"},
    {"pl":"przebierać się","en":"dress up"},
    {"pl":"pan młody","en":"groom"},
    {"pl":"mityczne stworzenie","en":"mythical creature"},
    {"pl":"parada, pochód","en":"parade"},
    {"pl":"ślub (ceremonia ślubna)","en":"wedding"},
    {"pl":"przynosić szczęście","en":"bring good luck"},
    {"pl":"zwyczaj","en":"custom"},
    {"pl":"pochodzić (z jakiegoś okresu)","en":"date back (to)"},
    {"pl":"podtrzymywać tradycje","en":"keep traditions alive"},
    {"pl":"źródło, pochodzenie","en":"origin"},
    {"pl":"brać udział w","en":"take part in"},
    {"pl":"tradycyjny strój","en":"traditional costume"},
    {"pl":"zaadaptować, ekranizować","en":"adapt"},
    {"pl":"autor","en":"author"},
    {"pl":"kompozytor","en":"composer"},
    {"pl":"tancerz","en":"dancer"},
    {"pl":"charakterystyczny element (np. obrazu), cecha charakterystyczna (np. recenzji)","en":"feature"},
    {"pl":"malarz","en":"painter"},
    {"pl":"popularny","en":"popular"},
    {"pl":"supergwiazda, wielka gwiazda","en":"superstar"},
    {"pl":"pisarz","en":"writer"},
    {"pl":"artystyczny","en":"artistic"},
    {"pl":"być opartym na (czymś), powstać na podstawie (czegoś)","en":"be based on (sth)"},
    {"pl":"być umiejscowionym (np. w XVI w.)","en":"be set in"},
    {"pl":"współczesny","en":"contemporary"},
    {"pl":"natychmiastowy sukces","en":"instant success"},
    {"pl":"legendarny","en":"legendary"},
    {"pl":"literacki","en":"literary"},
    {"pl":"tu: pobieranie tantiem","en":"collection of royalties"},
    {"pl":"treści (tworzone przez artystów); treść (np. tekstu)","en":"content"},
    {"pl":"pobierać, ściągać (np. pliki z internetu)","en":"download"},
    {"pl":"opłata","en":"fee"},
    {"pl":"dochód","en":"income"},
    {"pl":"nielegalnie skopiowane utwory muzyczne","en":"pirated music"},
    {"pl":"platforma streamingowa","en":"streaming service"}
  ]
}
